crontabber/__init__.py
crontabber/app.py
crontabber/base.py
crontabber/connection_factory.py
crontabber/datetimeutil.py
crontabber/dbapi2_util.py
crontabber/generic_app.py
crontabber/mixins.py
crontabber/transaction_executor.py
crontabber/tests/__init__.py
crontabber/tests/base.py
crontabber/tests/sampleapp.py
crontabber/tests/test_crontab_mixins.py
crontabber/tests/test_crontabber.py
crontabber/tests/test_datetimeutil.py
crontabber/tests/test_subprocess_mixin.py
crontabber/tests/test_transaction_executor.py
crontabber-0.18.1.dist-info/top_level.txt
crontabber-0.18.1.dist-info/entry_points.txt
crontabber-0.18.1.dist-info/METADATA
crontabber-0.18.1.dist-info/DESCRIPTION.rst
crontabber-0.18.1.dist-info/metadata.json
crontabber-0.18.1.dist-info/WHEEL
crontabber-0.18.1.dist-info/RECORD
