Metadata-Version: 2.0
Name: crontabber
Version: 0.18.1
Summary: A cron job runner with self-healing and job dependencies.
Home-page: https://github.com/mozilla/crontabber
Author: Peter Bengtsson
Author-email: peterbe@mozilla.com
License: UNKNOWN
Platform: UNKNOWN
Classifier: Development Status :: 4 - Beta
Classifier: License :: OSI Approved :: Mozilla Public License 2.0 (MPL 2.0)
Classifier: Operating System :: OS Independent
Classifier: Programming Language :: Python :: 2.7
Classifier: Topic :: Software Development :: Libraries :: Python Modules
Requires-Dist: configman (>1.2.3)
Requires-Dist: psycopg2 (>=2.4.5)
Requires-Dist: raven (>=3.4.1)
